mcp_prompt_tester/__init__.py
mcp_prompt_tester/__main__.py
mcp_prompt_tester/env.py
mcp_prompt_tester/server.py
mcp_prompt_tester/providers/__init__.py
mcp_prompt_tester/providers/anthropic.py
mcp_prompt_tester/providers/base.py
mcp_prompt_tester/providers/openai.py
mcp_prompt_tester/tools/__init__.py
mcp_prompt_tester/tools/list_providers.py
mcp_prompt_tester/tools/test_comparison.py
mcp_prompt_tester/tools/test_multiturn_conversation.py
mseep_mcp_prompt_tester-0.1.2.dist-info/METADATA
mseep_mcp_prompt_tester-0.1.2.dist-info/WHEEL
mseep_mcp_prompt_tester-0.1.2.dist-info/entry_points.txt
mseep_mcp_prompt_tester-0.1.2.dist-info/licenses/LICENSE
mseep_mcp_prompt_tester-0.1.2.dist-info/RECORD
