Metadata-Version: 2.4
Name: mseep-mcp-prompt-tester
Version: 0.1.2
Summary: MCP server for testing LLM prompts with different providers
Author-email: mseep <support@skydeck.ai>
License-File: LICENSE
Requires-Python: >=3.10
Requires-Dist: anthropic>=0.47.2
Requires-Dist: anyio>=4.5
Requires-Dist: click>=8.1.0
Requires-Dist: mcp>=1.3.0
Requires-Dist: openai>=1.64.0
Requires-Dist: python-dotenv>=1.0.0
